imgbasics/__init__.py
imgbasics/contours.py
imgbasics/cropping.py
imgbasics/transform.py
imgbasics-0.4.1.dist-info/licenses/LICENSE
tests/test_basics.py
tests/test_transform.py
imgbasics-0.4.1.dist-info/METADATA
imgbasics-0.4.1.dist-info/WHEEL
imgbasics-0.4.1.dist-info/top_level.txt
imgbasics-0.4.1.dist-info/RECORD
