Metadata-Version: 2.4
Name: imgbasics
Version: 0.4.1
Summary: Basic image analysis tools (cropping, contour properties, etc.)
Author-email: Olivier Vincent <ovinc.py@gmail.com>
License: BSD 3-Clause License
Project-URL: Homepage, https://github.com/ovinc/imgbasics
Project-URL: Documentation, https://github.com/ovinc/imgbasics/README.md
Project-URL: Repository, https://github.com/ovinc/imgbasics.git
Keywords: image,analysis,crop,imcrop,cropping,contour,contours,centroid,perimeter,area
Classifier: Programming Language :: Python :: 3
Classifier: Operating System :: OS Independent
Classifier: License :: OSI Approved :: BSD License
Requires-Python: >=3.6
License-File: LICENSE
Requires-Dist: matplotlib
Requires-Dist: numpy
Requires-Dist: importlib-metadata
Requires-Dist: drapo>=1.2.0
Provides-Extra: opencv
Requires-Dist: opencv-python; extra == "opencv"
Dynamic: license-file
